TraderBackTesterOptAlpha/TraderBackTesterDM.py
TraderBackTesterOptAlpha/TraderBackTesterUtils.py
TraderBackTesterOptAlpha/__init__.py
TraderBackTesterOptAlpha/version.py
traderbacktesteroptalpha-1.6.dist-info/LICENSE
traderbacktesteroptalpha-1.6.dist-info/METADATA
traderbacktesteroptalpha-1.6.dist-info/WHEEL
traderbacktesteroptalpha-1.6.dist-info/top_level.txt
traderbacktesteroptalpha-1.6.dist-info/RECORD
