Metadata-Version: 2.1
Name: traderbacktesteroptalpha
Version: 1.6
Summary: Package for backtesting trading strategies and updating required files
Home-page: UNKNOWN
Author: Vadlamani Rampratap Sharma
Author-email: rampratap.optalpha@gmail.com
License: MIT
Platform: UNKNOWN
Classifier: Programming Language :: Python :: 3
Classifier: License :: OSI Approved :: MIT License
Classifier: Operating System :: OS Independent
Requires-Python: >=3.9.7
License-File: LICENSE
Requires-Dist: pandas-ta==0.3.14b0
Requires-Dist: swifter==1.3.4
Requires-Dist: openpyxl==3.1.2
Requires-Dist: ta==0.10.2
Requires-Dist: pandas==1.5.3
Requires-Dist: numpy==1.23.5
